{
  "dgcp_version": "DGCP-DATASET-1.0",
  "dataset": "MaMeeFarm-Primary-Dataset",
  "data_unit_id": "01065",
  "file_path": "dataset/data-unit/01065/dataunit_01065.json",

  "category": "operations",
  "sub_category": "animal_feeding",

  "captured_at_local": "2026-02-08 06:49",
  "timezone": "Asia/Bangkok",
  "location": "MaMeeFarm",
  "zone": "HZ-02",
  "sub_zone": "yard_area",

  "data_type": "image",

  "title": "morning_dog_feeding_record",
  "summary": "Morning dog feeding activity observed in Zone HZ-02. Dry dog food pellets placed in a container with multiple dogs present around the feeding area.",

  "reference": {
    "dataunit_refs": ["01056"],
    "proof_refs": [],
    "note": "Reference to the previous evening dog feeding record."
  },

  "external_reference": {
    "binding": "non-binding",
    "storage": "pinata",
    "cid": "bafybeida3x6hnnud2aj2itaagxfs35ni2b3drc26zcbkdlkoad37cm7ouq",
    "note": "Raw image evidence stored on IPFS via Pinata gateway."
  },

  "media_count": 1,

  "integrity": {
    "hash_algorithm": "SHA-256",
    "hash_file": "dataset/data-unit/01065/hash/dataunit_01065.sha256",
    "ots_file": "dataset/data-unit/01065/ots/dgcp_dataunit_01065.ots"
  },

  "responsibility": {
    "actor": "MaMeeFarm operation",
    "recorded_by": "P'Toh",
    "accountability": "single-operator responsibility",
    "data_framework": "DGCP™"
  },

  "license": "DGCP | MMFARM-POL-2025"
}
